MANIFEST.in
README.txt
setup.py
collective/__init__.py
collective.plone3bugfixes.egg-info/PKG-INFO
collective.plone3bugfixes.egg-info/SOURCES.txt
collective.plone3bugfixes.egg-info/dependency_links.txt
collective.plone3bugfixes.egg-info/entry_points.txt
collective.plone3bugfixes.egg-info/namespace_packages.txt
collective.plone3bugfixes.egg-info/not-zip-safe
collective.plone3bugfixes.egg-info/paster_plugins.txt
collective.plone3bugfixes.egg-info/requires.txt
collective.plone3bugfixes.egg-info/top_level.txt
collective/plone3bugfixes/__init__.py
collective/plone3bugfixes/configure.zcml
collective/plone3bugfixes/interfaces.py
collective/plone3bugfixes/tests.py
collective/plone3bugfixes/browser/__init__.py
collective/plone3bugfixes/browser/configure.zcml
collective/plone3bugfixes/browser/ie7ish.pt
collective/plone3bugfixes/browser/resourceregistries.pt
collective/plone3bugfixes/locales/de/LC_MESSAGES/collective.plone3bugfixes.po
collective/plone3bugfixes/locales/en/LC_MESSAGES/collective.plone3bugfixes.po
collective/plone3bugfixes/locales/fr/LC_MESSAGES/collective.plone3bugfixes.po
collective/plone3bugfixes/profiles/default/browserlayer.xml
collective/plone3bugfixes/profiles/default/metadata.xml
collective/plone3bugfixes/profiles/default/skins.xml
collective/plone3bugfixes/skins/plone3bugfixes/IEFixes.css.dtml
collective/plone3bugfixes/skins/plone3bugfixes/IEFixes.css.dtml.metadata
collective/plone3bugfixes/skins/plone3bugfixes/livesearch_reply.py
collective/plone3bugfixes/skins/plone3bugfixes/member_search_results.pt
collective/plone3bugfixes/skins/plone3bugfixes/member_search_results.pt.metadata
collective/plone3bugfixes/skins/plone3bugfixes/search.pt
collective/plone3bugfixes/skins/plone3bugfixes/search.pt.metadata
collective/plone3bugfixes/skins/plone3bugfixes/search_form.pt
collective/plone3bugfixes/skins/plone3bugfixes/search_form.pt.metadata
docs/HISTORY.txt
docs/INSTALL.txt
docs/LICENSE.GPL
docs/LICENSE.txt