Metadata-Version: 1.0
Name: collective.plone3bugfixes
Version: 0.9.4
Summary: Plone 3 Bugfixes
Home-page: http://www.brainson.de/
Author: Brainson New Media GmbH, D9T GmbH
Author-email: info@brainson.de
License: GPL
Platform: UNKNOWN
Classifier: Framework :: Plone
Classifier: Programming Language :: Python
Classifier: Topic :: Software Development :: Libraries :: Python Modules
